easy_mitk/__init__.py
easy_mitk/dicom.py
easy_mitk/measure.py
easy_mitk/nifti.py
easy_mitk/utils/__init__.py
easy_mitk/utils/helper.py
easy_mitk-0.0.2.dist-info/LICENSE
easy_mitk-0.0.2.dist-info/METADATA
easy_mitk-0.0.2.dist-info/WHEEL
easy_mitk-0.0.2.dist-info/top_level.txt
easy_mitk-0.0.2.dist-info/RECORD
