Metadata-Version: 2.1
Name: easy-mitk
Version: 0.0.2
Summary: An easy-to-use Medical Imaging ToolKit
Home-page: https://gitee.com/daryl6/easy-mitk
Author: Daryl.Xu
Author-email: ziqiang_xu@qq.com
Classifier: Programming Language :: Python :: 3.7
Classifier: Operating System :: OS Independent
License-File: LICENSE
Requires-Dist: pydicom
Requires-Dist: nibabel
Requires-Dist: pylibjpeg-rle
Requires-Dist: dicom2nifti
Requires-Dist: numpy
Requires-Dist: vtk
